geneutils/__init__.py
geneutils/geneutils.py
geneutils-0.0.6.data/data/LICENSE
geneutils-0.0.6.dist-info/LICENSE
geneutils-0.0.6.dist-info/METADATA
geneutils-0.0.6.dist-info/WHEEL
geneutils-0.0.6.dist-info/entry_points.txt
geneutils-0.0.6.dist-info/top_level.txt
geneutils-0.0.6.dist-info/RECORD
