Metadata-Version: 2.1
Name: geneutils
Version: 0.0.6
Summary: CLI and utilities for Genetic analysis and database interface
Home-page: https://github.com/samapriya/geneutils
Author: Samapriya Roy
Author-email: samapriya.roy@gmail.com
License: MIT
Platform: UNKNOWN
Classifier: Development Status :: 3 - Alpha
Classifier: Intended Audience :: Developers
Classifier: Intended Audience :: Science/Research
Classifier: Natural Language :: English
Classifier: License :: OSI Approved :: Apache Software License
Classifier: Programming Language :: Python :: 3.6
Classifier: Programming Language :: Python :: 3.7
Classifier: Programming Language :: Python :: 3.8
Classifier: Programming Language :: Python :: 3.9
Classifier: Operating System :: OS Independent
Requires-Dist: biopython (>=1.77)
Requires-Dist: pandas (>=1.1.5)
Requires-Dist: requests (>=2.26.0)
Requires-Dist: beautifulsoup4 (>=4.9.3)
